x256offline/__init__.py
x256offline/x256.bin
x256offline/x256.py
x256offline-0.0.4.dist-info/LICENSE
x256offline-0.0.4.dist-info/METADATA
x256offline-0.0.4.dist-info/WHEEL
x256offline-0.0.4.dist-info/top_level.txt
x256offline-0.0.4.dist-info/RECORD
