Metadata-Version: 2.1
Name: x256offline
Version: 0.0.4
Summary: quickly find the nearest xterm 256 color index of an RGB
Author-email: userElaina <userelaina@pm.me>
Maintainer-email: userElaina <userelaina@pm.me>
License: MIT License
Project-URL: Homepage, https://github.com/userElaina/python-x256-offline
Project-URL: Bug Reports, https://github.com/userElaina/python-x256-offline/issues
Project-URL: Source, https://github.com/userElaina/python-x256-offline
Keywords: x256,xterm,color
Classifier: License :: OSI Approved :: MIT License
Classifier: Programming Language :: Python :: 3
Requires-Python: >=3.8
License-File: LICENSE
